.testr.conf
AUTHORS
ChangeLog
LICENSE
README.rst
babel.cfg
bandit.yaml
pylintrc
requirements.txt
setup.cfg
setup.py
test-requirements.txt
tox.ini
devstack/README.rst
devstack/plugin.sh
devstack/settings
doc/source/conf.py
doc/source/index.rst
doc/source/_static/.placeholder
etc/glare-paste.ini
etc/glare-swift.conf.sample
etc/glare.conf
etc/policy.json
etc/oslo-config-generator/glare.conf
glare/__init__.py
glare/engine.py
glare/i18n.py
glare/locking.py
glare/notification.py
glare/opts.py
glare/version.py
glare/wsgi.py
glare/api/__init__.py
glare/api/versions.py
glare/api/middleware/__init__.py
glare/api/middleware/context.py
glare/api/middleware/fault.py
glare/api/middleware/version_negotiation.py
glare/api/v1/__init__.py
glare/api/v1/api_version_request.py
glare/api/v1/api_versioning.py
glare/api/v1/resource.py
glare/api/v1/router.py
glare/cmd/__init__.py
glare/cmd/api.py
glare/cmd/db_manage.py
glare/common/__init__.py
glare/common/config.py
glare/common/exception.py
glare/common/policy.py
glare/common/semver_db.py
glare/common/store_api.py
glare/common/utils.py
glare/common/wsgi.py
glare/common/wsme_utils.py
glare/db/__init__.py
glare/db/api.py
glare/db/artifact_api.py
glare/db/migration/__init__.py
glare/db/migration/alembic.ini
glare/db/migration/migration.py
glare/db/migration/alembic_migrations/README
glare/db/migration/alembic_migrations/env.py
glare/db/migration/alembic_migrations/script.py.mako
glare/db/migration/alembic_migrations/versions/001_initial_version.py
glare/db/migration/alembic_migrations/versions/002_add_acquired_at_column.py
glare/db/sqlalchemy/__init__.py
glare/db/sqlalchemy/api.py
glare/db/sqlalchemy/models.py
glare/hacking/__init__.py
glare/hacking/checks.py
glare/objects/__init__.py
glare/objects/all.py
glare/objects/base.py
glare/objects/heat_environment.py
glare/objects/heat_template.py
glare/objects/image.py
glare/objects/murano_package.py
glare/objects/tosca_template.py
glare/objects/meta/__init__.py
glare/objects/meta/attribute.py
glare_dev.egg-info/PKG-INFO
glare_dev.egg-info/SOURCES.txt
glare_dev.egg-info/dependency_links.txt
glare_dev.egg-info/entry_points.txt
glare_dev.egg-info/not-zip-safe
glare_dev.egg-info/pbr.json
glare_dev.egg-info/requires.txt
glare_dev.egg-info/top_level.txt